setup.py
tag2env/__init__.py
tag2env/cli.py
tag2env.egg-info/PKG-INFO
tag2env.egg-info/SOURCES.txt
tag2env.egg-info/dependency_links.txt
tag2env.egg-info/entry_points.txt
tag2env.egg-info/not-zip-safe
tag2env.egg-info/requires.txt
tag2env.egg-info/top_level.txt