Metadata-Version: 1.1
Name: tag2env
Version: 0.1.1
Summary: Turns EC2 tags into environment variables
Home-page: https://github.com/ravenac95/tag2env
Author: Reuven V. Gonzales
Author-email: reuven@virtru.com
License: MIT
Platform: *nix
Classifier: Intended Audience :: Developers
Classifier: Programming Language :: Python
Classifier: Operating System :: POSIX
Classifier: Topic :: Software Development :: Build Tools
